litcharts/__init__.py
litcharts/_nbdev.py
litcharts/core.py
litcharts-0.0.1.dist-info/LICENSE
litcharts-0.0.1.dist-info/METADATA
litcharts-0.0.1.dist-info/WHEEL
litcharts-0.0.1.dist-info/entry_points.txt
litcharts-0.0.1.dist-info/top_level.txt
litcharts-0.0.1.dist-info/RECORD
