Metadata-Version: 2.1
Name: litcharts
Version: 0.0.1
Summary: Pythonic app development from within a notebook
Home-page: https://github.pylit-app.com/litcharts/litcharts/tree/master/
Author: Pylit Inc.
Author-email: info@pylit.app
License: Apache Software License 2.0
Keywords: python,data-science,data-analysis,machine-learning,data-visualization,developer-tools,jupyter,notebooks
Platform: UNKNOWN
Classifier: Development Status :: 3 - Alpha
Classifier: Intended Audience :: Developers
Classifier: Natural Language :: English
Classifier: Programming Language :: Python :: 3.6
Classifier: Programming Language :: Python :: 3.7
Classifier: Programming Language :: Python :: 3.8
Classifier: License :: OSI Approved :: Apache Software License
Requires-Python: >=3.6
Requires-Dist: pip
Requires-Dist: packaging
Provides-Extra: dev
